tempf/__init__.py
tempf/tempfiles.py
tempf-1.0.0.dist-info/LICENSE
tempf-1.0.0.dist-info/METADATA
tempf-1.0.0.dist-info/WHEEL
tempf-1.0.0.dist-info/RECORD
