Metadata-Version: 2.1
Name: tempf
Version: 1.0.0
Summary: Multiple temporary files in 1 line of code
Home-page: https://github.com/tomhea/tempfiles
License: BSD-2-Clause-Simplified
Keywords: esolang,oisc,assembly
Author: Tom Herman
Author-email: flipjumpproject@gmail.com
Requires-Python: >=3.7,<4.0
Classifier: Intended Audience :: Developers
Classifier: License :: Other/Proprietary License
Classifier: Operating System :: OS Independent
Classifier: Programming Language :: Python :: 3
Classifier: Programming Language :: Python :: 3.7
Classifier: Programming Language :: Python :: 3.8
Classifier: Programming Language :: Python :: 3.9
Classifier: Programming Language :: Python :: 3.10
Classifier: Programming Language :: Python :: 3.11
Classifier: Programming Language :: Python :: 3.12
Classifier: Topic :: Software Development :: Libraries
Classifier: Topic :: System :: Filesystems
Provides-Extra: tests
Requires-Dist: pytest (>=7.4.3,<8.0.0) ; extra == "tests"
Project-URL: Repository, https://github.com/tomhea/tempfiles
